CHANGES.rst
MANIFEST.in
README.rst
setup.py
doc/Makefile
doc/make.bat
doc/source/changes.rst
doc/source/conf.py
doc/source/databases.rst
doc/source/denoising_illumina.rst
doc/source/formats.rst
doc/source/index.rst
doc/source/install.rst
doc/source/otu.rst
doc/source/pairedend_97.rst
doc/source/phyloseq.rst
doc/source/picrust.rst
doc/source/singleend.rst
doc/source/table.rst
doc/source/_templates/layout.html
doc/source/commands/classify.rst
doc/source/commands/convert.rst
doc/source/commands/filter.rst
doc/source/commands/filterstats.rst
doc/source/commands/merge.rst
doc/source/commands/mergepairs.rst
doc/source/commands/msa.rst
doc/source/commands/otu.rst
doc/source/commands/root.rst
doc/source/commands/split.rst
doc/source/commands/stats.rst
doc/source/commands/tablebar.rst
doc/source/commands/tablerare.rst
doc/source/commands/tablestats.rst
doc/source/commands/tabletotax.rst
doc/source/commands/tobiom.rst
doc/source/commands/tree.rst
doc/source/commands/trim.rst
doc/source/images/filterstats454.png
doc/source/images/garda_alpha.png
doc/source/images/garda_alpha2.png
doc/source/images/garda_bar.png
doc/source/images/garda_beta.png
doc/source/images/garda_rarecurves.png
doc/source/images/garda_stats_plot.png
doc/source/images/garda_stats_qualsumm_plot.png
doc/source/images/garda_taxtable2.png
doc/source/images/read454.png
doc/source/images/readpaired.png
docker/Dockerfile
docker/README.md
micca/__init__.py
micca/argutils.py
micca/ioutils.py
micca/seq.py
micca/table.py
micca/tax.py
micca.egg-info/PKG-INFO
micca.egg-info/SOURCES.txt
micca.egg-info/dependency_links.txt
micca.egg-info/requires.txt
micca.egg-info/top_level.txt
micca/api/__init__.py
micca/api/_convert.py
micca/api/_filter.py
micca/api/_filterstats.py
micca/api/_merge.py
micca/api/_mergepairs.py
micca/api/_split.py
micca/api/_stats.py
micca/api/_tobiom.py
micca/api/_trim.py
micca/api/classify.py
micca/api/msa.py
micca/api/otu.py
micca/api/root.py
micca/api/table.py
micca/api/tree.py
micca/cmds/__init__.py
micca/cmds/classify.py
micca/cmds/convert.py
micca/cmds/filter.py
micca/cmds/filterstats.py
micca/cmds/merge.py
micca/cmds/mergepairs.py
