Metadata-Version: 1.2
Name: micca
Version: 1.7.2
Summary: micca - MICrobial Community Analysis
Home-page: http://www.micca.org
Author: Davide Albanese
Author-email: davide.albanese@fmach.it
Maintainer: Davide Albanese
Maintainer-email: davide.albanese@fmach.it
License: GPLv3
Download-URL: http://www.micca.org
Platform: UNKNOWN
Classifier: Development Status :: 5 - Production/Stable
Classifier: Intended Audience :: Science/Research
Classifier: License :: OSI Approved :: GNU General Public License (GPL)
Classifier: Programming Language :: Python :: 2
Classifier: Programming Language :: C
Classifier: Programming Language :: C++
Classifier: Topic :: Scientific/Engineering :: Bio-Informatics
Classifier: Environment :: Console
Classifier: Operating System :: MacOS :: MacOS X
Classifier: Operating System :: POSIX :: Linux
